beautypy/static/images/nav.png
beautypy/static/node_modules/.package-lock.json
beautypy/static/node_modules/@popperjs/core/LICENSE.md
beautypy/static/node_modules/@popperjs/core/README.md
beautypy/static/node_modules/@popperjs/core/index.d.ts
beautypy/static/node_modules/@popperjs/core/package.json
beautypy/static/node_modules/@popperjs/core/dist/cjs/enums.js
beautypy/static/node_modules/@popperjs/core/dist/cjs/enums.js.flow
beautypy/static/node_modules/@popperjs/core/dist/cjs/enums.js.map
beautypy/static/node_modules/@popperjs/core/dist/cjs/popper-base.js
beautypy/static/node_modules/@popperjs/core/dist/cjs/popper-base.js.flow
beautypy/static/node_modules/@popperjs/core/dist/cjs/popper-base.js.map
beautypy/static/node_modules/@popperjs/core/dist/cjs/popper-lite.js
beautypy/static/node_modules/@popperjs/core/dist/cjs/popper-lite.js.flow
beautypy/static/node_modules/@popperjs/core/dist/cjs/popper-lite.js.map
beautypy/static/node_modules/@popperjs/core/dist/cjs/popper.js
beautypy/static/node_modules/@popperjs/core/dist/cjs/popper.js.flow
beautypy/static/node_modules/@popperjs/core/dist/cjs/popper.js.map
beautypy/static/node_modules/@popperjs/core/dist/esm/createPopper.js
beautypy/static/node_modules/@popperjs/core/dist/esm/enums.js
beautypy/static/node_modules/@popperjs/core/dist/esm/index.js
beautypy/static/node_modules/@popperjs/core/dist/esm/popper-base.js
beautypy/static/node_modules/@popperjs/core/dist/esm/popper-lite.js
beautypy/static/node_modules/@popperjs/core/dist/esm/popper.js
beautypy/static/node_modules/@popperjs/core/dist/esm/types.js
beautypy/static/node_modules/@popperjs/core/dist/esm/dom-utils/contains.js
beautypy/static/node_modules/@popperjs/core/dist/esm/dom-utils/getBoundingClientRect.js
beautypy/static/node_modules/@popperjs/core/dist/esm/dom-utils/getClippingRect.js
beautypy/static/node_modules/@popperjs/core/dist/esm/dom-utils/getCompositeRect.js
beautypy/static/node_modules/@popperjs/core/dist/esm/dom-utils/getComputedStyle.js
beautypy-1.0.dist-info/licenses/LICENSE
beautypy-1.0.dist-info/METADATA
beautypy-1.0.dist-info/WHEEL
beautypy-1.0.dist-info/top_level.txt
beautypy-1.0.dist-info/RECORD
