Metadata-Version: 2.4
Name: beautypy
Version: 1.0
Summary: Reusable Django UI components and tags with Tailwind support
Author-email: Avinash Chaurasiya <avinashchaurasiya902@gmail.com>
License: MIT License
Keywords: django,tailwind,template tags,ui,components
Requires-Python: >=3.7
License-File: LICENSE
Requires-Dist: django>=4.0
Dynamic: license-file
